trackertools/__init__.py
trackertools/helpers.py
trackertools-0.1.6.dist-info/DESCRIPTION.rst
trackertools-0.1.6.dist-info/METADATA
trackertools-0.1.6.dist-info/RECORD
trackertools-0.1.6.dist-info/WHEEL
trackertools-0.1.6.dist-info/metadata.json
trackertools-0.1.6.dist-info/top_level.txt
