Metadata-Version: 2.0
Name: trackertools
Version: 0.1.6
Summary: Tools to manage Gazelle tracker user account
Home-page: https://pypi.python.org/pypi/trackertools
Author: Lionel Young
Author-email: lionelyoung@gmail.com
License: MIT
Keywords: private tracker tools gazelle trackers
Platform: UNKNOWN
Classifier: Development Status :: 3 - Alpha
Classifier: Intended Audience :: Developers
Classifier: License :: OSI Approved :: MIT License
Classifier: Programming Language :: Python :: 2.7
Requires-Dist: lxml
Requires-Dist: mechanize
Requires-Dist: requests
